MANIFEST.in
README.rst
setup.cfg
setup.py
monk_tf/__init__.py
monk_tf/conn.py
monk_tf/dev.py
monk_tf/fixture.py
test/test_conn.py
test/test_dev.py
test/test_fixture.py
tmonk.egg-info/PKG-INFO
tmonk.egg-info/SOURCES.txt
tmonk.egg-info/dependency_links.txt
tmonk.egg-info/not-zip-safe
tmonk.egg-info/requires.txt
tmonk.egg-info/top_level.txt