Metadata-Version: 1.1
Name: tmonk
Version: 0.1.1
Summary: thesis build of DFE's MONK
Home-page: https://github.com/erikb85/thesis-monk
Author: DResearch Fahrzeugelektronik GmbH
Author-email: project-monk@dresearch-fe.de
License:                     GNU GENERAL PUBLIC LICENSE
